varname/__init__.py
varname/core.py
varname/helpers.py
varname/ignore.py
varname/py.typed
varname/utils.py
varname-0.15.0.dist-info/LICENSE
varname-0.15.0.dist-info/METADATA
varname-0.15.0.dist-info/WHEEL
varname-0.15.0.dist-info/RECORD
