Metadata-Version: 2.3
Name: varname
Version: 0.15.0
Summary: Dark magics about variable names in python.
License: MIT
Author: pwwang
Author-email: pwwang@pwwang.com
Requires-Python: >=3.8,<4.0
Classifier: License :: OSI Approved :: MIT License
Classifier: Programming Language :: Python :: 3
Classifier: Programming Language :: Python :: 3.8
Classifier: Programming Language :: Python :: 3.9
Classifier: Programming Language :: Python :: 3.10
Classifier: Programming Language :: Python :: 3.11
Classifier: Programming Language :: Python :: 3.12
Classifier: Programming Language :: Python :: 3.13
Provides-Extra: all
Requires-Dist: asttokens (==3.*) ; extra == "all"
Requires-Dist: executing (>=2.1,<3.0)
Requires-Dist: pure_eval (==0.*) ; extra == "all"
Requires-Dist: typing_extensions (>=4.13,<5.0) ; python_version < "3.10"
Project-URL: Homepage, https://github.com/pwwang/python-varname
Project-URL: Repository, https://github.com/pwwang/python-varname
